{
  "id": 45,
  "collectionType": "users",
  "Email": "jsawyer.person@gmail.com",
  "Password": "[hidden]",
  "Username": "JackEBoi",
  "Full Name": null,
  "First Name": "jack",
  "Photo": {
    "url": "https://adalo-uploads.imgix.net/0a2d2b7c5f3378814f9131da7bc60387406e5a22b51d7a5195db857c50d77de9.jpeg",
    "size": 2115190,
    "width": 2268,
    "height": 4032,
    "filename": "IMG_5293.jpeg",
    "metadata": {
      "width": 2268,
      "height": 4032,
      "blurHash": "eaEMzboIInRjad%%WAs;V@RP.AoJj[WBRj%hoeaxV[WBXAofn%jtj[",
      "blurHashWidth": 32
    }
  },
  "Gender": "male",
  "Attracted to": "female",
  "Age": 28,
  "City": {
    "name": "Austin",
    "placeId": "ChIJLwPMoJm1RIYRetVp1EtGm10",
    "coordinates": {
      "latitude": 30.267153,
      "longitude": -97.7430608
    },
    "fullAddress": "Austin, TX, USA",
    "addressElements": {
      "city": "Austin",
      "region": "Texas",
      "country": "United States",
      "address1": "",
      "address2": "",
      "postalCode": ""
    }
  },
  "How to Approach Me": "salutation",
  "Is Event Creator": null,
  "Is Event Attendee": false,
  "Is Message Sender": null,
  "Is Message Receiver": null,
  "Is Not Event Attendee": null,
  "Check in for event": [
    177
  ],
  "User Agrees to Terms & Conditions & rivacy Policy": true,
  "Subscribed": null,
  "Instagram Handle": null,
  "Show face dismissed": true,
  "admin": null,
  "wants to look at event?": null,
  "Is Place Attendee": null,
  "Is Not Place Attendee": null,
  "Is Place Creator?": null,
  "created_at": "2025-01-17T06:41:07.298Z",
  "updated_at": "2025-06-06T23:20:05.632Z",
  "downloadedAt": "2025-06-27T18:30:21.029Z"
}