{
  "id": 169,
  "collectionType": "users",
  "Email": "hsgreses@yahoo.com",
  "Password": "[hidden]",
  "Username": null,
  "Full Name": null,
  "First Name": "hannah",
  "Photo": {
    "url": "https://adalo-uploads.imgix.net/efa3da0cbb9a48c3080b7a153ed3e2c2fb7fea69acc73b9b6adb4545921974f5.jpg",
    "size": 1619756,
    "width": 3088,
    "height": 2316,
    "filename": "image.jpg",
    "metadata": {
      "width": 3088,
      "height": 2316,
      "blurHash": "e77Kbt-oo}XTE1NdR*t7t6oL0KXSs.i^-p={-oR*NHNG%NNGNHxvRj",
      "blurHashWidth": 32
    }
  },
  "Gender": null,
  "Attracted to": null,
  "Age": null,
  "City": null,
  "How to Approach Me": null,
  "Is Event Creator": null,
  "Is Event Attendee": null,
  "Is Message Sender": null,
  "Is Message Receiver": null,
  "Is Not Event Attendee": null,
  "User Agrees to Terms & Conditions & rivacy Policy": true,
  "Subscribed": null,
  "Instagram Handle": null,
  "Show face dismissed": null,
  "admin": null,
  "wants to look at event?": null,
  "Is Place Attendee": null,
  "Is Not Place Attendee": null,
  "Is Place Creator?": null,
  "created_at": "2025-02-23T00:46:56.043Z",
  "updated_at": "2025-02-23T00:46:56.043Z",
  "downloadedAt": "2025-06-27T18:30:31.552Z"
}