{
  "id": 88,
  "email": "chriswest2015@yahoo.com",
  "firstName": "Christian",
  "gender": "Male",
  "age": 27,
  "city": {
    "name": "Austin",
    "placeId": "ChIJLwPMoJm1RIYRetVp1EtGm10",
    "coordinates": {
      "latitude": 30.267153,
      "longitude": -97.7430608
    },
    "fullAddress": "Austin, TX, USA",
    "addressElements": {
      "city": "Austin",
      "region": "Texas",
      "country": "United States",
      "address1": "",
      "address2": "",
      "postalCode": ""
    }
  },
  "attractedTo": "Female",
  "howToApproachMe": "Don’t be shy😌 I am chill",
  "instagramHandle": "iam.cwest",
  "photo": {
    "originalUrl": "https://adalo-uploads.imgix.net/79ea4c4a179139e3077309ec7ca6ecd0eee0cd109aff6366b621e86a19c41e51.jpeg",
    "filename": "IMG_1607.jpeg",
    "size": 4070990,
    "width": 4032,
    "height": 3024
  },
  "createdAt": "2025-02-14T00:07:13.378Z",
  "updatedAt": "2025-05-24T14:46:07.573Z"
}