{
  "id": 555,
  "collectionType": "users",
  "Email": "robert.gloverm@gmail.com",
  "Password": "[hidden]",
  "Username": null,
  "Full Name": null,
  "First Name": "Robert",
  "Photo": {
    "url": "https://adalo-uploads.imgix.net/75f23715e8c86d3cb1d14107a5b2c216aa18774192f68826fb086c55642c84c6.jpg",
    "size": 831446,
    "width": 2250,
    "height": 3000,
    "filename": "IMG_0411.jpg",
    "metadata": {
      "width": 2250,
      "height": 3000,
      "blurHash": "eH7mIBxW#z#*xJ9:NGJYJpNYj:xIxHsosj,_SKabniWbJ4jbX9S#k8",
      "blurHashWidth": 32
    }
  },
  "Gender": null,
  "Attracted to": null,
  "Age": null,
  "City": null,
  "How to Approach Me": null,
  "Is Event Creator": null,
  "Is Event Attendee": false,
  "Is Message Sender": null,
  "Is Message Receiver": null,
  "Is Not Event Attendee": null,
  "Check in for event": [
    127
  ],
  "User Agrees to Terms & Conditions & rivacy Policy": true,
  "Subscribed": null,
  "Instagram Handle": null,
  "Show face dismissed": null,
  "admin": null,
  "wants to look at event?": true,
  "Is Place Attendee": null,
  "Is Not Place Attendee": null,
  "Is Place Creator?": null,
  "created_at": "2025-05-31T17:06:20.827Z",
  "updated_at": "2025-05-31T17:06:39.568Z",
  "downloadedAt": "2025-06-27T18:31:04.503Z"
}