{
  "id": 143,
  "collectionType": "users",
  "Email": "bhavishkathuri7@gmail.com",
  "Password": "[hidden]",
  "Username": "Bhavishkathuri7",
  "Full Name": null,
  "First Name": "Bhavish",
  "Photo": {
    "url": "https://adalo-uploads.imgix.net/ec8686ce62529fc3402b5482df2d2454b3c284b796bc863cab23ec589f2b277b.jpeg",
    "size": 1647478,
    "width": 3024,
    "height": 4032,
    "filename": "IMG_3883.jpeg",
    "metadata": {
      "width": 3024,
      "height": 4032,
      "blurHash": "eTFEx^^%Eh%0s.0hIqniENbbIqNHxWw]Rk-nxsWEs:t5VtV[R+R+WC",
      "blurHashWidth": 32
    }
  },
  "Gender": "Male",
  "Attracted to": "Female",
  "Age": 25,
  "City": {
    "name": "Austin",
    "placeId": "ChIJLwPMoJm1RIYRetVp1EtGm10",
    "coordinates": {
      "latitude": 30.267153,
      "longitude": -97.7430608
    },
    "fullAddress": "Austin, TX, USA",
    "addressElements": {
      "city": "Austin",
      "region": "Texas",
      "country": "United States",
      "address1": "",
      "address2": "",
      "postalCode": ""
    }
  },
  "How to Approach Me": "Say Hi",
  "Is Event Creator": null,
  "Is Event Attendee": false,
  "Is Message Sender": null,
  "Is Message Receiver": null,
  "Is Not Event Attendee": false,
  "User Agrees to Terms & Conditions & rivacy Policy": true,
  "Subscribed": null,
  "Instagram Handle": null,
  "Show face dismissed": null,
  "admin": null,
  "wants to look at event?": null,
  "Is Place Attendee": null,
  "Is Not Place Attendee": null,
  "Is Place Creator?": null,
  "created_at": "2025-02-22T17:54:49.308Z",
  "updated_at": "2025-02-23T01:53:09.960Z",
  "downloadedAt": "2025-06-27T18:30:29.902Z"
}