{
  "id": 200,
  "collectionType": "users",
  "Email": "sandersjordan60@gmail.com",
  "Password": "[hidden]",
  "Username": null,
  "Full Name": null,
  "First Name": "Jordan",
  "Photo": {
    "url": "https://adalo-uploads.imgix.net/5103fcd3ced3659e347f5182f5382009043314e42a0917ccc66312946f3f43b6.jpeg",
    "size": 688619,
    "width": 1536,
    "height": 2048,
    "filename": "IMG_1333.jpeg",
    "metadata": {
      "width": 1536,
      "height": 2048,
      "blurHash": "exFPpwXTXTX9r=T#o#jFoLbbS*ofn$WXW=nPfkbbbHn%NHoLbIoeWB",
      "blurHashWidth": 32
    }
  },
  "Gender": "female",
  "Attracted to": "Male",
  "Age": 22,
  "City": {
    "name": "Austin",
    "placeId": "ChIJLwPMoJm1RIYRetVp1EtGm10",
    "coordinates": {
      "latitude": 30.267153,
      "longitude": -97.7430608
    },
    "fullAddress": "Austin, TX, USA",
    "addressElements": {
      "city": "Austin",
      "region": "Texas",
      "country": "United States",
      "address1": "",
      "address2": "",
      "postalCode": ""
    }
  },
  "How to Approach Me": null,
  "Is Event Creator": null,
  "Is Event Attendee": false,
  "Is Message Sender": null,
  "Is Message Receiver": null,
  "Is Not Event Attendee": null,
  "Check in for event": [
    211
  ],
  "User Agrees to Terms & Conditions & rivacy Policy": true,
  "Subscribed": null,
  "Instagram Handle": "@jordan_e_sanders",
  "Show face dismissed": null,
  "admin": null,
  "wants to look at event?": false,
  "Is Place Attendee": null,
  "Is Not Place Attendee": null,
  "Is Place Creator?": null,
  "created_at": "2025-03-09T02:27:13.236Z",
  "updated_at": "2025-06-11T00:21:04.221Z",
  "downloadedAt": "2025-06-27T18:30:34.649Z"
}