{
  "id": 328,
  "collectionType": "users",
  "Email": "lolaporq@yahoo.com",
  "Password": "[hidden]",
  "Username": null,
  "Full Name": null,
  "First Name": "Victor ",
  "Photo": {
    "url": "https://adalo-uploads.imgix.net/2c759507ece9c25ff3f97e6ddc8282a869b3ac86341b5fa77379fcf35f82902b.jpeg",
    "size": 46364,
    "width": 528,
    "height": 528,
    "filename": "IMG_1299.jpeg",
    "metadata": {
      "width": 528,
      "height": 528,
      "blurHash": "eA9j1B~VO@t,%g6AXn?F%Lx[=_oeIpnOn$M|V@r;RPRPNwNHM|i_s9",
      "blurHashWidth": 32
    }
  },
  "Gender": null,
  "Attracted to": null,
  "Age": null,
  "City": null,
  "How to Approach Me": null,
  "Is Event Creator": null,
  "Is Event Attendee": null,
  "Is Message Sender": null,
  "Is Message Receiver": null,
  "Is Not Event Attendee": null,
  "User Agrees to Terms & Conditions & rivacy Policy": true,
  "Subscribed": null,
  "Instagram Handle": null,
  "Show face dismissed": true,
  "admin": null,
  "wants to look at event?": null,
  "Is Place Attendee": null,
  "Is Not Place Attendee": null,
  "Is Place Creator?": null,
  "created_at": "2025-04-11T16:54:17.736Z",
  "updated_at": "2025-04-11T16:54:28.663Z",
  "downloadedAt": "2025-06-27T18:30:47.289Z"
}