{
  "id": 368,
  "collectionType": "users",
  "Email": "laurenR_Tatro@yahoo.com",
  "Password": "[hidden]",
  "Username": "lotatro ",
  "Full Name": null,
  "First Name": "lauren ",
  "Photo": {
    "url": "https://adalo-uploads.imgix.net/bdbe915d9b572c63b0d80f5111958913ac595a6237cbc79023cbbc763b736663.jpeg",
    "size": 1331358,
    "width": 1775,
    "height": 3153,
    "filename": "IMG_7863.jpeg",
    "metadata": {
      "width": 1775,
      "height": 3153,
      "blurHash": "eEHxj34T_MV@IB~qkBM|IVt6.7%MIBoet7IVxuxZWBM{xZofWVafWB",
      "blurHashWidth": 32
    }
  },
  "Gender": "female",
  "Attracted to": "men",
  "Age": 30,
  "City": {
    "name": "Austin",
    "placeId": "ChIJLwPMoJm1RIYRetVp1EtGm10",
    "coordinates": {
      "latitude": 30.267153,
      "longitude": -97.7430608
    },
    "fullAddress": "Austin, TX, USA",
    "addressElements": {
      "city": "Austin",
      "region": "Texas",
      "country": "United States",
      "address1": "",
      "address2": "",
      "postalCode": ""
    }
  },
  "How to Approach Me": "no sudden movements. I am easily frightened and will run ",
  "Is Event Creator": null,
  "Is Event Attendee": null,
  "Is Message Sender": null,
  "Is Message Receiver": null,
  "Is Not Event Attendee": null,
  "User Agrees to Terms & Conditions & rivacy Policy": true,
  "Subscribed": null,
  "Instagram Handle": "@lotatro",
  "Show face dismissed": true,
  "admin": null,
  "wants to look at event?": null,
  "Is Place Attendee": null,
  "Is Not Place Attendee": null,
  "Is Place Creator?": null,
  "created_at": "2025-04-18T21:31:41.492Z",
  "updated_at": "2025-04-18T21:34:03.085Z",
  "downloadedAt": "2025-06-27T18:30:50.622Z"
}